Solvers/__init__.py
Solvers/Core/CP_Solver_GOT.py
Solvers/Core/CP_Solver_Number_of_Instances.py
Solvers/Core/Component.py
Solvers/Core/ManuverSolver.py
Solvers/Core/ManuverSolver_SB.py
Solvers/Core/ProblemDefinition.py
Solvers/Core/__init__.py
Solvers/Core/conflictGraph.py
Solvers/Core/Restrictions/RestrictionConflicts.py
Solvers/Core/Restrictions/RestrictionDependences.py
Solvers/Core/Restrictions/RestrictionFixComponents.py
Solvers/Core/Restrictions/RestrictionHardware.py
Solvers/Core/Restrictions/RestrictionNumberOfInstances.py
Solvers/Core/Restrictions/__init__.py
Solvers/Formalization1/__init__.py
Solvers/Formalization1/CPLEX/CP_CPLEX_Solver.py
Solvers/Formalization1/CPLEX/CP_CPLEX_Solver_Enc_AllCombinationsOffers.py
Solvers/Formalization1/CPLEX/__init__.py
Solvers/Formalization1/Z3/SMT_Solver_Z3.py
Solvers/Formalization1/Z3/SMT_Solver_Z3_Int_SB_AllCombinationsOffers.py
Solvers/Formalization1/Z3/__init__.py
Solvers/Formalization2/__init__.py
Solvers/Formalization2/CPLEX/CP_CPLEX_Solver.py
Solvers/Formalization2/CPLEX/CP_CPLEX_Solver_Enc_AllCombinationsOffers.py
Solvers/Formalization2/CPLEX/__init__.py
Solvers/Formalization2/Z3/SMT_Solver_Z3_Int_SB_AllCombinationsOffers.py
Solvers/Formalization2/Z3/SMT_Solver_Z3_Parent.py
Solvers/Formalization2/Z3/__init__.py
src/__init__.py
src/conflictGraph.py
src/init.py
src/model.py
src/smt.py
src/surrogate.py
src/sym_breaker.py
sage_rec_engine-0.2.dist-info/LICENSE.md
sage_rec_engine-0.2.dist-info/METADATA
sage_rec_engine-0.2.dist-info/WHEEL
sage_rec_engine-0.2.dist-info/top_level.txt
sage_rec_engine-0.2.dist-info/RECORD
