Metadata-Version: 2.1
Name: sage-rec-engine
Version: 0.2
Summary: Automated cloud deployment
Home-page: https://github.com/SAGE-Project/SAGE-Engine
Author: Madalina Erascu
Author-email: madalina.erascu@e-uvt.ro
Classifier: Programming Language :: Python :: 3
Classifier: Programming Language :: Python :: 3.8
License-File: LICENSE.md
